srunbit/__init__.py
srunbit/cli/__init__.py
srunbit/cli/command.py
srunbit/encrypt/__init__.py
srunbit/encrypt/hash.py
srunbit/model/__init__.py
srunbit/model/account.py
srunbit/model/form.py
srunbit/network/__init__.py
srunbit/network/network.py
srunbit/store/__init__.py
srunbit/store/account.py
srun_cli_bit-0.1.5.dist-info/LICENSE
srun_cli_bit-0.1.5.dist-info/METADATA
srun_cli_bit-0.1.5.dist-info/WHEEL
srun_cli_bit-0.1.5.dist-info/entry_points.txt
srun_cli_bit-0.1.5.dist-info/top_level.txt
srun_cli_bit-0.1.5.dist-info/RECORD
