Metadata-Version: 2.1
Name: srun-cli-bit
Version: 0.1.5
Summary: A cli tool for BIT campus network.
Home-page: https://github.com/c-my/srun-cli-bit
Author: Cai Mingyang
Author-email: cai.my@outlook.com
Classifier: Programming Language :: Python :: 3.6
Classifier: License :: OSI Approved :: GNU General Public License v3 (GPLv3)
Classifier: Operating System :: OS Independent
License-File: LICENSE
Requires-Dist: requests
